{
    "asset": {
        "format": "jpg",
        "id": "3eefa23401e0ed04c93942c7fa2892db",
        "name": "DJI_0101_JPG.rf.12c90b96aba71119b152874eb02f2d57.jpg",
        "path": "file:/Users/mohamedkhanafer/Documents/GitHub/TrainYourOwnYOLO/Data/Source_Images/Training_Images/DJI_0101_JPG.rf.12c90b96aba71119b152874eb02f2d57.jpg",
        "size": {
            "width": 416,
            "height": 416
        },
        "state": 2,
        "type": 1
    },
    "regions": [
        {
            "id": "M36NIPlEy",
            "type": "RECTANGLE",
            "tags": [
                "sheep"
            ],
            "boundingBox": {
                "height": 49.634659746251444,
                "width": 40.89677047289504,
                "left": 93.88264129181084,
                "top": 48.27205882352941
            },
            "points": [
                {
                    "x": 93.88264129181084,
                    "y": 48.27205882352941
                },
                {
                    "x": 134.77941176470588,
                    "y": 48.27205882352941
                },
                {
                    "x": 134.77941176470588,
                    "y": 97.90671856978085
                },
                {
                    "x": 93.88264129181084,
                    "y": 97.90671856978085
                }
            ]
        },
        {
            "id": "Ay6mESBo7",
            "type": "RECTANGLE",
            "tags": [
                "sheep"
            ],
            "boundingBox": {
                "height": 60.76225490196078,
                "width": 27.714965397923876,
                "left": 135.70717993079583,
                "top": 6.7099192618223755
            },
            "points": [
                {
                    "x": 135.70717993079583,
                    "y": 6.7099192618223755
                },
                {
                    "x": 163.42214532871972,
                    "y": 6.7099192618223755
                },
                {
                    "x": 163.42214532871972,
                    "y": 67.47217416378317
                },
                {
                    "x": 135.70717993079583,
                    "y": 67.47217416378317
                }
            ]
        },
        {
            "id": "a1Ht3bVDw",
            "type": "RECTANGLE",
            "tags": [
                "sheep"
            ],
            "boundingBox": {
                "height": 42.43555363321799,
                "width": 32.931084198385236,
                "left": 104.82280853517878,
                "top": 12.801326412918108
            },
            "points": [
                {
                    "x": 104.82280853517878,
                    "y": 12.801326412918108
                },
                {
                    "x": 137.75389273356402,
                    "y": 12.801326412918108
                },
                {
                    "x": 137.75389273356402,
                    "y": 55.2368800461361
                },
                {
                    "x": 104.82280853517878,
                    "y": 55.2368800461361
                }
            ]
        }
    ],
    "version": "2.2.0"
}