{
    "asset": {
        "format": "jpg",
        "id": "7c7711978d2d3300b4e48f30838d9cd3",
        "name": "eb3cb10929f5083ed1584d05fb1d4e9fe777ead218ac104497f5c978a6ebb3bf_640.jpg",
        "path": "file:/Users/mohamedkhanafer/Documents/GitHub/TrainYourOwnYOLO/Data/Source_Images/Training_Images/eb3cb10929f5083ed1584d05fb1d4e9fe777ead218ac104497f5c978a6ebb3bf_640.jpg",
        "size": {
            "width": 640,
            "height": 418
        },
        "state": 2,
        "type": 1
    },
    "regions": [
        {
            "id": "0O5U0CZhW",
            "type": "RECTANGLE",
            "tags": [
                "sheep"
            ],
            "boundingBox": {
                "height": 333.4823180379747,
                "width": 595.2646815550041,
                "left": 0,
                "top": 84.51768196202532
            },
            "points": [
                {
                    "x": 0,
                    "y": 84.51768196202532
                },
                {
                    "x": 595.2646815550041,
                    "y": 84.51768196202532
                },
                {
                    "x": 595.2646815550041,
                    "y": 418.00000000000006
                },
                {
                    "x": 0,
                    "y": 418.00000000000006
                }
            ]
        }
    ],
    "version": "2.2.0"
}