{
    "asset": {
        "format": "jpeg",
        "id": "91fe7f59f8a6f7f1656e7ec16a1ed8ef",
        "name": "OIP-Y9Lc3aBXRdO_I3lyNwIecQAAAA.jpeg",
        "path": "file:/Users/mohamedkhanafer/Documents/GitHub/TrainYourOwnYOLO/Data/Source_Images/Training_Images/OIP-Y9Lc3aBXRdO_I3lyNwIecQAAAA.jpeg",
        "size": {
            "width": 200,
            "height": 300
        },
        "state": 2,
        "type": 1
    },
    "regions": [
        {
            "id": "AFEL3alUF",
            "type": "RECTANGLE",
            "tags": [
                "elephant"
            ],
            "boundingBox": {
                "height": 292.39430147058823,
                "width": 188.34883217993078,
                "left": 3.368295847750865,
                "top": 4.122512975778546
            },
            "points": [
                {
                    "x": 3.368295847750865,
                    "y": 4.122512975778546
                },
                {
                    "x": 191.71712802768164,
                    "y": 4.122512975778546
                },
                {
                    "x": 191.71712802768164,
                    "y": 296.51681444636677
                },
                {
                    "x": 3.368295847750865,
                    "y": 296.51681444636677
                }
            ]
        }
    ],
    "version": "2.2.0"
}