{
    "asset": {
        "format": "jpg",
        "id": "4eed317c3dce30e5ad44e08dd6152eb3",
        "name": "e99_jpg.rf.cb587534813e9653356030dc1788a45f.jpg",
        "path": "file:/Users/mohamedkhanafer/Documents/GitHub/TrainYourOwnYOLO/Data/Source_Images/Training_Images/e99_jpg.rf.cb587534813e9653356030dc1788a45f.jpg",
        "size": {
            "width": 416,
            "height": 416
        },
        "state": 2,
        "type": 1
    },
    "regions": [
        {
            "id": "sV6vXK_S8",
            "type": "RECTANGLE",
            "tags": [
                "elephant"
            ],
            "boundingBox": {
                "height": 104.5866493656286,
                "width": 154.8135813148789,
                "left": 105.66435986159169,
                "top": 103.04974048442907
            },
            "points": [
                {
                    "x": 105.66435986159169,
                    "y": 103.04974048442907
                },
                {
                    "x": 260.4779411764706,
                    "y": 103.04974048442907
                },
                {
                    "x": 260.4779411764706,
                    "y": 207.63638985005767
                },
                {
                    "x": 105.66435986159169,
                    "y": 207.63638985005767
                }
            ]
        },
        {
            "id": "FFNUUtZM3",
            "type": "RECTANGLE",
            "tags": [
                "elephant"
            ],
            "boundingBox": {
                "height": 104.62226066897347,
                "width": 125.01066897347174,
                "left": 178.50259515570934,
                "top": 195.86966551326412
            },
            "points": [
                {
                    "x": 178.50259515570934,
                    "y": 195.86966551326412
                },
                {
                    "x": 303.5132641291811,
                    "y": 195.86966551326412
                },
                {
                    "x": 303.5132641291811,
                    "y": 300.4919261822376
                },
                {
                    "x": 178.50259515570934,
                    "y": 300.4919261822376
                }
            ]
        }
    ],
    "version": "2.2.0"
}