{
    "asset": {
        "format": "jpg",
        "id": "1a998045a5c3bab3cf552985f58ddcf2",
        "name": "e114_png.rf.dada2ab8b0244974d9012268ec6e0601.jpg",
        "path": "file:/Users/mohamedkhanafer/Documents/GitHub/TrainYourOwnYOLO/Data/Source_Images/Training_Images/e114_png.rf.dada2ab8b0244974d9012268ec6e0601.jpg",
        "size": {
            "width": 416,
            "height": 416
        },
        "state": 2,
        "type": 1
    },
    "regions": [
        {
            "id": "oidZla24t",
            "type": "RECTANGLE",
            "tags": [
                "elephant"
            ],
            "boundingBox": {
                "height": 99.54296424452133,
                "width": 68.6229815455594,
                "left": 317.4597750865052,
                "top": 219.37125144175317
            },
            "points": [
                {
                    "x": 317.4597750865052,
                    "y": 219.37125144175317
                },
                {
                    "x": 386.08275663206456,
                    "y": 219.37125144175317
                },
                {
                    "x": 386.08275663206456,
                    "y": 318.9142156862745
                },
                {
                    "x": 317.4597750865052,
                    "y": 318.9142156862745
                }
            ]
        },
        {
            "id": "Zky6XeAJy",
            "type": "RECTANGLE",
            "tags": [
                "elephant"
            ],
            "boundingBox": {
                "height": 76.50994809688581,
                "width": 57.64532871972318,
                "left": 242.2168396770473,
                "top": 301.55276816608995
            },
            "points": [
                {
                    "x": 242.2168396770473,
                    "y": 301.55276816608995
                },
                {
                    "x": 299.86216839677047,
                    "y": 301.55276816608995
                },
                {
                    "x": 299.86216839677047,
                    "y": 378.06271626297575
                },
                {
                    "x": 242.2168396770473,
                    "y": 378.06271626297575
                }
            ]
        },
        {
            "id": "LDuzECZJC",
            "type": "RECTANGLE",
            "tags": [
                "elephant"
            ],
            "boundingBox": {
                "height": 66.86303344867359,
                "width": 80.38595732410612,
                "left": 335.61404267589387,
                "top": 349.1369665513264
            },
            "points": [
                {
                    "x": 335.61404267589387,
                    "y": 349.1369665513264
                },
                {
                    "x": 416,
                    "y": 349.1369665513264
                },
                {
                    "x": 416,
                    "y": 416
                },
                {
                    "x": 335.61404267589387,
                    "y": 416
                }
            ]
        },
        {
            "id": "jmLyYdDUe",
            "type": "RECTANGLE",
            "tags": [
                "elephant"
            ],
            "boundingBox": {
                "height": 119.68209342560553,
                "width": 94.78229527104959,
                "left": 133.10005767012686,
                "top": 296.31790657439444
            },
            "points": [
                {
                    "x": 133.10005767012686,
                    "y": 296.31790657439444
                },
                {
                    "x": 227.88235294117646,
                    "y": 296.31790657439444
                },
                {
                    "x": 227.88235294117646,
                    "y": 416
                },
                {
                    "x": 133.10005767012686,
                    "y": 416
                }
            ]
        },
        {
            "id": "zOgc9EvTG",
            "type": "RECTANGLE",
            "tags": [
                "elephant"
            ],
            "boundingBox": {
                "height": 93.88264129181084,
                "width": 69.01283160322953,
                "left": 47.179354094579004,
                "top": 261.82742214532874
            },
            "points": [
                {
                    "x": 47.179354094579004,
                    "y": 261.82742214532874
                },
                {
                    "x": 116.19218569780853,
                    "y": 261.82742214532874
                },
                {
                    "x": 116.19218569780853,
                    "y": 355.7100634371395
                },
                {
                    "x": 47.179354094579004,
                    "y": 355.7100634371395
                }
            ]
        },
        {
            "id": "yFtKGHl7v",
            "type": "RECTANGLE",
            "tags": [
                "elephant"
            ],
            "boundingBox": {
                "height": 72.93569780853518,
                "width": 86.68728373702422,
                "left": 33.57396193771626,
                "top": 343.06430219146483
            },
            "points": [
                {
                    "x": 33.57396193771626,
                    "y": 343.06430219146483
                },
                {
                    "x": 120.26124567474048,
                    "y": 343.06430219146483
                },
                {
                    "x": 120.26124567474048,
                    "y": 416
                },
                {
                    "x": 33.57396193771626,
                    "y": 416
                }
            ]
        },
        {
            "id": "lwZoS23hu",
            "type": "RECTANGLE",
            "tags": [
                "elephant"
            ],
            "boundingBox": {
                "height": 113.89806805074971,
                "width": 82.91248558246828,
                "left": 73.3780276816609,
                "top": 133.28186274509804
            },
            "points": [
                {
                    "x": 73.3780276816609,
                    "y": 133.28186274509804
                },
                {
                    "x": 156.29051326412917,
                    "y": 133.28186274509804
                },
                {
                    "x": 156.29051326412917,
                    "y": 247.17993079584775
                },
                {
                    "x": 73.3780276816609,
                    "y": 247.17993079584775
                }
            ]
        },
        {
            "id": "1c88TxTUY",
            "type": "RECTANGLE",
            "tags": [
                "elephant"
            ],
            "boundingBox": {
                "height": 114.39287773933103,
                "width": 60.021914648212224,
                "left": 162.13264129181084,
                "top": 153.82396193771626
            },
            "points": [
                {
                    "x": 162.13264129181084,
                    "y": 153.82396193771626
                },
                {
                    "x": 222.15455594002307,
                    "y": 153.82396193771626
                },
                {
                    "x": 222.15455594002307,
                    "y": 268.2168396770473
                },
                {
                    "x": 162.13264129181084,
                    "y": 268.2168396770473
                }
            ]
        },
        {
            "id": "vvaoxl2sO",
            "type": "RECTANGLE",
            "tags": [
                "elephant"
            ],
            "boundingBox": {
                "height": 112.56170703575548,
                "width": 69.8618800461361,
                "left": 0,
                "top": 54.76268742791234
            },
            "points": [
                {
                    "x": 0,
                    "y": 54.76268742791234
                },
                {
                    "x": 69.8618800461361,
                    "y": 54.76268742791234
                },
                {
                    "x": 69.8618800461361,
                    "y": 167.32439446366783
                },
                {
                    "x": 0,
                    "y": 167.32439446366783
                }
            ]
        },
        {
            "id": "mjTmr2gnX",
            "type": "RECTANGLE",
            "tags": [
                "elephant"
            ],
            "boundingBox": {
                "height": 79.65498846597463,
                "width": 68.69982698961938,
                "left": 70.12615340253748,
                "top": 34.548587081891576
            },
            "points": [
                {
                    "x": 70.12615340253748,
                    "y": 34.548587081891576
                },
                {
                    "x": 138.82598039215685,
                    "y": 34.548587081891576
                },
                {
                    "x": 138.82598039215685,
                    "y": 114.20357554786621
                },
                {
                    "x": 70.12615340253748,
                    "y": 114.20357554786621
                }
            ]
        },
        {
            "id": "r284qFsjD",
            "type": "RECTANGLE",
            "tags": [
                "elephant"
            ],
            "boundingBox": {
                "height": 100.42762399077277,
                "width": 55.28373702422145,
                "left": 221.5716551326413,
                "top": 32.603085351787776
            },
            "points": [
                {
                    "x": 221.5716551326413,
                    "y": 32.603085351787776
                },
                {
                    "x": 276.85539215686276,
                    "y": 32.603085351787776
                },
                {
                    "x": 276.85539215686276,
                    "y": 133.03070934256056
                },
                {
                    "x": 221.5716551326413,
                    "y": 133.03070934256056
                }
            ]
        },
        {
            "id": "EAkKlfosJ",
            "type": "RECTANGLE",
            "tags": [
                "elephant"
            ],
            "boundingBox": {
                "height": 101.81833910034602,
                "width": 67.12168396770473,
                "left": 276.5405132641292,
                "top": 19.4868800461361
            },
            "points": [
                {
                    "x": 276.5405132641292,
                    "y": 19.4868800461361
                },
                {
                    "x": 343.6621972318339,
                    "y": 19.4868800461361
                },
                {
                    "x": 343.6621972318339,
                    "y": 121.30521914648212
                },
                {
                    "x": 276.5405132641292,
                    "y": 121.30521914648212
                }
            ]
        },
        {
            "id": "bK1Qt5nVt",
            "type": "RECTANGLE",
            "tags": [
                "elephant"
            ],
            "boundingBox": {
                "height": 90.20717993079585,
                "width": 70.05305651672434,
                "left": 159.8235294117647,
                "top": 45.4868800461361
            },
            "points": [
                {
                    "x": 159.8235294117647,
                    "y": 45.4868800461361
                },
                {
                    "x": 229.87658592848905,
                    "y": 45.4868800461361
                },
                {
                    "x": 229.87658592848905,
                    "y": 135.69405997693195
                },
                {
                    "x": 159.8235294117647,
                    "y": 135.69405997693195
                }
            ]
        },
        {
            "id": "xYDrNiDDw",
            "type": "RECTANGLE",
            "tags": [
                "elephant"
            ],
            "boundingBox": {
                "height": 122.14864475201846,
                "width": 57.701557093425606,
                "left": 240.7811418685121,
                "top": 142.3365051903114
            },
            "points": [
                {
                    "x": 240.7811418685121,
                    "y": 142.3365051903114
                },
                {
                    "x": 298.48269896193773,
                    "y": 142.3365051903114
                },
                {
                    "x": 298.48269896193773,
                    "y": 264.4851499423299
                },
                {
                    "x": 240.7811418685121,
                    "y": 264.4851499423299
                }
            ]
        },
        {
            "id": "I5ZJyE_ni",
            "type": "RECTANGLE",
            "tags": [
                "elephant"
            ],
            "boundingBox": {
                "height": 76.95977508650519,
                "width": 41.543396770472896,
                "left": 231.6027970011534,
                "top": 241.3527970011534
            },
            "points": [
                {
                    "x": 231.6027970011534,
                    "y": 241.3527970011534
                },
                {
                    "x": 273.1461937716263,
                    "y": 241.3527970011534
                },
                {
                    "x": 273.1461937716263,
                    "y": 318.31257208765857
                },
                {
                    "x": 231.6027970011534,
                    "y": 318.31257208765857
                }
            ]
        },
        {
            "id": "VLtb054bY",
            "type": "RECTANGLE",
            "tags": [
                "elephant"
            ],
            "boundingBox": {
                "height": 66.83117070357555,
                "width": 49.07987312572087,
                "left": 288.7345732410611,
                "top": 143.97462514417532
            },
            "points": [
                {
                    "x": 288.7345732410611,
                    "y": 143.97462514417532
                },
                {
                    "x": 337.814446366782,
                    "y": 143.97462514417532
                },
                {
                    "x": 337.814446366782,
                    "y": 210.80579584775086
                },
                {
                    "x": 288.7345732410611,
                    "y": 210.80579584775086
                }
            ]
        },
        {
            "id": "Hk6Di6kQc",
            "type": "RECTANGLE",
            "tags": [
                "elephant"
            ],
            "boundingBox": {
                "height": 72.30968858131487,
                "width": 54.200403690888116,
                "left": 143.95025951557093,
                "top": 3.4955305651672433
            },
            "points": [
                {
                    "x": 143.95025951557093,
                    "y": 3.4955305651672433
                },
                {
                    "x": 198.15066320645906,
                    "y": 3.4955305651672433
                },
                {
                    "x": 198.15066320645906,
                    "y": 75.80521914648212
                },
                {
                    "x": 143.95025951557093,
                    "y": 75.80521914648212
                }
            ]
        }
    ],
    "version": "2.2.0"
}