{
    "asset": {
        "format": "jpg",
        "id": "df9682597c32ff2a134772f6740c95c0",
        "name": "ea36b70f29f2013ed1584d05fb1d4e9fe777ead218ac104497f5c978a6e8b0b1_640.jpg",
        "path": "file:/Users/mohamedkhanafer/Documents/GitHub/TrainYourOwnYOLO/Data/Source_Images/Training_Images/ea36b70f29f2013ed1584d05fb1d4e9fe777ead218ac104497f5c978a6e8b0b1_640.jpg",
        "size": {
            "width": 640,
            "height": 392
        },
        "state": 2,
        "type": 1
    },
    "regions": [
        {
            "id": "gCPm0DWMH",
            "type": "RECTANGLE",
            "tags": [
                "sheep"
            ],
            "boundingBox": {
                "height": 379.26644736842104,
                "width": 568.3581472291149,
                "left": 71.64185277088502,
                "top": 2.291708839406208
            },
            "points": [
                {
                    "x": 71.64185277088502,
                    "y": 2.291708839406208
                },
                {
                    "x": 640,
                    "y": 2.291708839406208
                },
                {
                    "x": 640,
                    "y": 381.55815620782727
                },
                {
                    "x": 71.64185277088502,
                    "y": 381.55815620782727
                }
            ]
        }
    ],
    "version": "2.2.0"
}